Metadata-Version: 2.1
Name: darkseed
Version: 0.0.23
Summary: a Pelican theme for the Botanixxx blog.
Home-page: https://github.com/blackforestbotanics/darkseed
Author: Tom Spalding
Author-email: tom@blackforestbotanics.com
License: MIT
Platform: UNKNOWN
Classifier: Framework :: Pelican :: Themes
Classifier: Programming Language :: Python :: 3
Classifier: License :: OSI Approved :: MIT License
